{
  "required": true,
  "minVersion": "0.8",
  "package": "io.github.ultimateboomer.textweaks.mixin",
  "compatibilityLevel": "JAVA_16",
  "plugin": "io.github.ultimateboomer.textweaks.TexTweaksMixinPlugin",
  "client": [
    "ChestBlockEntityRendererMixin",
    "MinecraftClientGameMixin",
    "MinecraftClientMixin",
    "MipmapHelperMixin",
    "ReloadableResourceManagerImplMixin",
    "RenderLayerMixin",
    "SpriteAtlasTextureMixin",
    "TextureStitcherMixin",
    "TextureUtilMixin",
    "MissingSpriteMixin"
  ],
  "injectors": {
    "defaultRequire": 1
  }
}
